daml_client/__init__.py
daml_client/daml_client.py.py
daml_client-1.0.3.dist-info/METADATA
daml_client-1.0.3.dist-info/WHEEL
daml_client-1.0.3.dist-info/top_level.txt
daml_client-1.0.3.dist-info/RECORD
