Metadata-Version: 2.1
Name: daml-client
Version: 1.0.3
Summary: A demo for python packaging.
Home-page: https://github.com/xxx
Author: yut-75
Author-email: xiao3952@foxmail.com
License: MIT
Keywords: demo
Platform: UNKNOWN
